robka/__init__.py
robka/api.py
robka/asynco.py
robka/button.py
robka/config.py
robka/context.py
robka/decorators.py
robka/exceptions.py
robka/jobs.py
robka/keyboards.py
robka/keypad.py
robka/logger.py
robka/utils.py
robka/adaptorrubka/__init__.py
robka/adaptorrubka/enums.py
robka/adaptorrubka/exceptions.py
robka/adaptorrubka/client/__init__.py
robka/adaptorrubka/client/client.py
robka/adaptorrubka/crypto/__init__.py
robka/adaptorrubka/crypto/crypto.py
robka/adaptorrubka/methods/__init__.py
robka/adaptorrubka/methods/methods.py
robka/adaptorrubka/network/__init__.py
robka/adaptorrubka/network/helper.py
robka/adaptorrubka/network/network.py
robka/adaptorrubka/network/socket.py
robka/adaptorrubka/sessions/__init__.py
robka/adaptorrubka/sessions/sessions.py
robka/adaptorrubka/types/__init__.py
robka/adaptorrubka/types/socket/__init__.py
robka/adaptorrubka/types/socket/message.py
robka/adaptorrubka/utils/__init__.py
robka/adaptorrubka/utils/configs.py
robka/adaptorrubka/utils/utils.py
robka-2.4.2.dist-info/METADATA
robka-2.4.2.dist-info/WHEEL
robka-2.4.2.dist-info/top_level.txt
robka-2.4.2.dist-info/RECORD
