Metadata-Version: 2.1
Name: robka
Version: 2.4.2
Summary: A professional and localized Python library for interacting with Rubika Bot API, compatible with various systems.
Home-page: https://pypi.org/project/robka/
Author: httex
Author-email: 
Maintainer: httex
Maintainer-email: 
License: UNKNOWN
Platform: UNKNOWN
Classifier: Programming Language :: Python :: 3
Classifier: License :: OSI Approved :: MIT License
Classifier: Operating System :: OS Independent
Classifier: Topic :: Communications :: Chat
Classifier: Topic :: Software Development :: Libraries
Requires-Python: >=3.6
Requires-Dist: Pillow
Requires-Dist: aiofiles
Requires-Dist: aiohttp
Requires-Dist: filetype
Requires-Dist: mutagen
Requires-Dist: pycryptodome
Requires-Dist: requests
Requires-Dist: tqdm
Requires-Dist: websocket-client
